_libtimetag.cpython-37m-darwin.so
libtimetag/__init__.py
libtimetag-0.9.2.dist-info/LICENSE
libtimetag-0.9.2.dist-info/METADATA
libtimetag-0.9.2.dist-info/WHEEL
libtimetag-0.9.2.dist-info/top_level.txt
libtimetag-0.9.2.dist-info/RECORD
