Metadata-Version: 2.1
Name: libtimetag
Version: 0.9.2
Summary: Library for storage and processing of time-correlated single-photon counting (TCSPC) data.
Home-page: https://www.github.com/rabouwlab/libtimetag
Author: Stijn Hinterding
Author-email: git@stijnhinterding.nl
License: UNKNOWN
Platform: UNKNOWN
Classifier: Programming Language :: Python :: 3
Classifier: License :: OSI Approved :: MIT License
Classifier: Operating System :: OS Independent
Requires-Python: >=3.6
Requires-Dist: numpy
Requires-Dist: python-dateutil
